BinaryCraft.py
__init__.py
setup.py
BinaryCraft-1.0.0.dist-info/License.txt
BinaryCraft-1.0.0.dist-info/METADATA
BinaryCraft-1.0.0.dist-info/WHEEL
BinaryCraft-1.0.0.dist-info/top_level.txt
BinaryCraft-1.0.0.dist-info/RECORD
