Metadata-Version: 2.1
Name: BinaryCraft
Version: 1.0.0
Summary: A Python script to convert files to binary format and back
Author-email: ayyandirai <ayyandiraiayyandirai345@gmail.com>
Project-URL: Homepage, https://github.com/pypa/sampleproject
Project-URL: Bug Tracker, https://github.com/pypa/sampleproject/issues
Classifier: Programming Language :: Python :: 3
Classifier: License :: OSI Approved :: MIT License
Classifier: Operating System :: OS Independent
Requires-Python: >=3.7
License-File: License.txt
